<?xml version="1.0"?>
<!--<!DOCTYPE metadata SYSTEM "http://www.esri.com/metadata/esriprof80.dtd">-->
<metadata xml:lang="es"><Esri><CreaDate>20210406</CreaDate><CreaTime>14073900</CreaTime><SyncOnce>TRUE</SyncOnce><ArcGISFormat>1.0</ArcGISFormat></Esri><idinfo><citation><citeinfo><onlink Sync="TRUE">\\PAOLA-F4A944FB7\D$\BPR\SHP\geo_articulo</onlink></citeinfo></citation></idinfo><distInfo><distributor><distorTran><onLineSrc><linkage Sync="TRUE">file://\\PAOLA-F4A944FB7\D$\BPR\SHP\geo_articulo</linkage><protocol Sync="TRUE">Local Area Network</protocol></onLineSrc></distorTran></distributor></distInfo><dataqual><lineage><procstep><procdesc Sync="TRUE">Dataset copied.</procdesc><srcused Sync="TRUE">D:\Ginebra\Interpretacion\geo_articulo</srcused><date Sync="TRUE">20100602</date><time Sync="TRUE">23123700</time></procstep><procstep><procdesc Sync="TRUE">Dataset copied.</procdesc><srcused Sync="TRUE">E:\Ginebra\Interpretacion\geo_articulo</srcused><procdate Sync="TRUE">20110305</procdate><proctime Sync="TRUE">09215800</proctime></procstep></lineage></dataqual></metadata>
